{
  "version": "1.0.0",
  "rss": "<LINK TO RSS FEED>",
  "discord": {
    "clientId": "<FILL IN OR REMOVE DISCORD OBJECT>",
    "smallImageText": "<FILL IN OR REMOVE DISCORD OBJECT>",
    "smallImageKey": "<FILL IN OR REMOVE DISCORD OBJECT>"
  },
  "servers": [
    {
      "id": "Naruto-1.7.10",
      "name": "Naruto",
      "description": "Naruto Arcane (1.7.10)",
      "icon": "https://i.imgur.com/JIXpxAS.jpeg",
      "version": "1.0.0",
      "address": "51.222.255.229:10138",
      "minecraftVersion": "1.7.10",
      "discord": {
        "shortId": "<FILL IN OR REMOVE DISCORD OBJECT>",
        "largeImageText": "<FILL IN OR REMOVE DISCORD OBJECT>",
        "largeImageKey": "<FILL IN OR REMOVE DISCORD OBJECT>"
      },
      "mainServer": true,
      "autoconnect": true,
      "modules": [
        {
          "id": "net.minecraftforge:forge:1.7.10-10.13.4.1614-1.7.10:universal",
          "name": "Minecraft Forge",
          "type": "ForgeHosted",
          "artifact": {
            "size": 3018833,
            "MD5": "add0fba161c4652a96efb4264ec2d9ec",
            "url": "https://github.com/SogimaYT/launcher-files/blob/main/repo/lib/net/minecraftforge/forge/1.7.10-10.13.4.1614-1.7.10/forge-1.7.10-10.13.4.1614-1.7.10-universal.jar"
          },
          "subModules": [
            {
              "id": "net.minecraft:launchwrapper:1.12@jar",
              "name": "Minecraft Forge (launchwrapper)",
              "type": "Library",
              "artifact": {
                "size": 32999,
                "MD5": "934b2d91c7c5be4a49577c9e6b40e8da",
                "url": "https://github.com/SogimaYT/launcher-files/blob/main/repo/lib/net/minecraft/launchwrapper/1.12/launchwrapper-1.12.jar"
              }
            },
            {
              "id": "org.ow2.asm:asm-all:5.0.3@jar",
              "name": "Minecraft Forge (asm-all)",
              "type": "Library",
              "artifact": {
                "size": 241639,
                "MD5": "c5cc4613bbdfba3ccf5f0ab85390d0b8",
                "url": "https://github.com/SogimaYT/launcher-files/blob/main/repo/lib/org/ow2/asm/asm-all/5.0.3/asm-all-5.0.3.jar"
              }
            },
            {
              "id": "com.typesafe.akka:akka-actor_2.11:2.3.3@jar",
              "name": "Minecraft Forge (akka-actor_2.11)",
              "type": "Library",
              "artifact": {
                "size": 2514991,
                "MD5": "541440ca0819ebada47d6d1a8b3ee9e1",
                "url": "https://github.com/SogimaYT/launcher-files/blob/main/repo/lib/com/typesafe/akka/akka-actor_2.11/2.3.3/akka-actor_2.11-2.3.3.jar"
              }
            },
            {
              "id": "com.typesafe:config:1.2.1@jar",
              "name": "Minecraft Forge (config)",
              "type": "Library",
              "artifact": {
                "size": 219554,
                "MD5": "3aaf3c6e76a68e732c17d4a7e9877d81",
                "url": "https://github.com/SogimaYT/launcher-files/blob/main/repo/lib/com/typesafe/config/1.2.1/config-1.2.1.jar"
              }
            },
            {
              "id": "org.scala-lang:scala-actors-migration_2.11:1.1.0@jar",
              "name": "Minecraft Forge (scala-actors-migration_2.11)",
              "type": "Library",
              "artifact": {
                "size": 58018,
                "MD5": "f5e79398daa1806f8b17311a3c782723",
                "url": "https://github.com/SogimaYT/launcher-files/blob/main/repo/lib/org/scala-lang/scala-actors-migration_2.11/1.1.0/scala-actors-migration_2.11-1.1.0.jar"
              }
            },
            {
              "id": "org.scala-lang:scala-compiler:2.11.1@jar",
              "name": "Minecraft Forge (scala-compiler)",
              "type": "Library",
              "artifact": {
                "size": 13449765,
                "MD5": "06030143bf86ca896fb6ccfd679b5760",
                "url": "https://github.com/SogimaYT/launcher-files/blob/main/repo/lib/org/scala-lang/scala-compiler/2.11.1/scala-compiler-2.11.1.jar"
              }
            },
            {
              "id": "org.scala-lang.plugins:scala-continuations-library_2.11:1.0.2@jar",
              "name": "Minecraft Forge (scala-continuations-library_2.11)",
              "type": "Library",
              "artifact": {
                "size": 25365,
                "MD5": "004d7007abbcee858d3ca2c3ccbcbaab",
                "url": "https://github.com/SogimaYT/launcher-files/blob/main/repo/lib/org/scala-lang/plugins/scala-continuations-library_2.11/1.0.2/scala-continuations-library_2.11-1.0.2.jar"
              }
            },
            {
              "id": "org.scala-lang.plugins:scala-continuations-plugin_2.11.1:1.0.2@jar",
              "name": "Minecraft Forge (scala-continuations-plugin_2.11.1)",
              "type": "Library",
              "artifact": {
                "size": 206575,
                "MD5": "359c4a6743a082c689039482eed78670",
                "url": "https://github.com/SogimaYT/launcher-files/blob/main/repo/lib/org/scala-lang/plugins/scala-continuations-plugin_2.11.1/1.0.2/scala-continuations-plugin_2.11.1-1.0.2.jar"
              }
            },
            {
              "id": "org.scala-lang:scala-library:2.11.1@jar",
              "name": "Minecraft Forge (scala-library)",
              "type": "Library",
              "artifact": {
                "size": 5538130,
                "MD5": "1d88f665219e6006c5dd82d71c525c0f",
                "url": "https://github.com/SogimaYT/launcher-files/blob/main/repo/lib/org/scala-lang/scala-library/2.11.1/scala-library-2.11.1.jar"
              }
            },
            {
              "id": "org.scala-lang:scala-parser-combinators_2.11:1.0.1@jar",
              "name": "Minecraft Forge (scala-parser-combinators_2.11)",
              "type": "Library",
              "artifact": {
                "size": 419701,
                "MD5": "4e694499c965af4a02599c99d4f0b196",
                "url": "https://github.com/SogimaYT/launcher-files/blob/main/repo/lib/org/scala-lang/scala-parser-combinators_2.11/1.0.1/scala-parser-combinators_2.11-1.0.1.jar"
              }
            },
            {
              "id": "org.scala-lang:scala-reflect:2.11.1@jar",
              "name": "Minecraft Forge (scala-reflect)",
              "type": "Library",
              "artifact": {
                "size": 4372892,
                "MD5": "7878fac044e4e4b576bb35a77ccc34fc",
                "url": "https://github.com/SogimaYT/launcher-files/blob/main/repo/lib/org/scala-lang/scala-reflect/2.11.1/scala-reflect-2.11.1.jar"
              }
            },
            {
              "id": "org.scala-lang:scala-swing_2.11:1.0.1@jar",
              "name": "Minecraft Forge (scala-swing_2.11)",
              "type": "Library",
              "artifact": {
                "size": 726500,
                "MD5": "1009d69e4948045383f2a7a334348af5",
                "url": "https://github.com/SogimaYT/launcher-files/blob/main/repo/lib/org/scala-lang/scala-swing_2.11/1.0.1/scala-swing_2.11-1.0.1.jar"
              }
            },
            {
              "id": "org.scala-lang:scala-xml_2.11:1.0.2@jar",
              "name": "Minecraft Forge (scala-xml_2.11)",
              "type": "Library",
              "artifact": {
                "size": 648679,
                "MD5": "c2d7e66495afe14545c31b21e99879ef",
                "url": "https://github.com/SogimaYT/launcher-files/blob/main/repo/lib/org/scala-lang/scala-xml_2.11/1.0.2/scala-xml_2.11-1.0.2.jar"
              }
            },
            {
              "id": "lzma:lzma:0.0.1@jar",
              "name": "Minecraft Forge (lzma)",
              "type": "Library",
              "artifact": {
                "size": 5762,
                "MD5": "a3e3c3186e41c4a1a3027ba2bb23cdc6",
                "url": "https://github.com/SogimaYT/launcher-files/blob/main/repo/lib/lzma/lzma/0.0.1/lzma-0.0.1.jar"
              }
            },
            {
              "id": "net.sf.jopt-simple:jopt-simple:4.5@jar",
              "name": "Minecraft Forge (jopt-simple)",
              "type": "Library",
              "artifact": {
                "size": 61311,
                "MD5": "1372bd4823bb1ef61e7db6724f601150",
                "url": "https://github.com/SogimaYT/launcher-files/blob/main/repo/lib/net/sf/jopt-simple/jopt-simple/4.5/jopt-simple-4.5.jar"
              }
            },
            {
              "id": "com.google.guava:guava:17.0@jar",
              "name": "Minecraft Forge (guava)",
              "type": "Library",
              "artifact": {
                "size": 2243036,
                "MD5": "89fef81c2adfa9b50a64ed5cd5d8c155",
                "url": "https://github.com/SogimaYT/launcher-files/blob/main/repo/lib/com/google/guava/guava/17.0/guava-17.0.jar"
              }
            },
            {
              "id": "org.apache.commons:commons-lang3:3.3.2@jar",
              "name": "Minecraft Forge (commons-lang3)",
              "type": "Library",
              "artifact": {
                "size": 412739,
                "MD5": "3128bf75a2549ebe38663401191bacab",
                "url": "https://github.com/SogimaYT/launcher-files/blob/main/repo/lib/org/apache/commons/commons-lang3/3.3.2/commons-lang3-3.3.2.jar"
              }
            }
          ]
        },
        {
          "id": "ru.timeconqueror.spongemixins.core:unimixins:0.1.19@jar",
          "name": "UniMixins",
          "type": "ForgeMod",
          "artifact": {
            "size": 5239985,
            "url": "https://github.com/SogimaYT/launcher-files/blob/main/servers/Naruto-1.7.10/forgemods/required/+unimixins-all-1.7.10-0.1.19.jar",
            "MD5": "f3c47bebe224ed677a9551265e9d7aa1"
          }
        },
        {
          "id": "generated.forgemod:armourersWorkshop:1.7.10-0.48.5@jar",
          "name": "Armourer's Workshop",
          "type": "ForgeMod",
          "artifact": {
            "size": 2089120,
            "url": "https://github.com/SogimaYT/launcher-files/blob/main/servers/Naruto-1.7.10/forgemods/required/Armourers-Workshop-1.7.10-0.48.5.jar",
            "MD5": "19885ea7a6b598516b4e7e467e32b2bb"
          }
        },
        {
          "id": "generated.forgemod:crowhpbar:1.0@jar",
          "name": "Crow's HP Bar",
          "type": "ForgeMod",
          "artifact": {
            "size": 865529,
            "url": "https://github.com/SogimaYT/launcher-files/blob/main/servers/Naruto-1.7.10/forgemods/optionalon/crowHud.jar",
            "MD5": "1fbce2d2eef9470ff169cfc793ac272b"
          },
          "required": {
            "value": false
          }
        },
        {
          "id": "org.spongepowered.asm.launch:customnpcs:1.11.1@jar",
          "name": "CustomNPC+",
          "type": "ForgeMod",
          "artifact": {
            "size": 17834817,
            "url": "https://github.com/SogimaYT/launcher-files/blob/main/servers/Naruto-1.7.10/forgemods/required/CustomNPC-Plus-1.11.1.jar",
            "MD5": "72c4fc0cf7c0df57a57f43c993442d8a"
          }
        },
        {
          "id": "generated.forgemod:dragonblockc:v1.4.85@jar",
          "name": "DragonBlockC",
          "type": "ForgeMod",
          "artifact": {
            "size": 15118442,
            "url": "https://github.com/SogimaYT/launcher-files/blob/main/servers/Naruto-1.7.10/forgemods/required/DragonBlockC-v1.4.85.jar",
            "MD5": "c50cf9fac71d3e851c2fc3e17ff72d48"
          }
        },
        {
          "id": "generated.forgemod:geckolib3:v3.0.0-master.7+604c673d58@jar",
          "name": "GeckoLib",
          "type": "ForgeMod",
          "artifact": {
            "size": 3572688,
            "url": "https://github.com/SogimaYT/launcher-files/blob/main/servers/Naruto-1.7.10/forgemods/required/geckolib-unofficial-1.7.10-1.0.3.jar",
            "MD5": "422759795119fa69a3928d7884fe8764"
          }
        },
        {
          "id": "generated.forgemod:gkmodlib:unspecified@jar",
          "name": "Gkmodlib",
          "type": "ForgeMod",
          "artifact": {
            "size": 3798391,
            "url": "https://github.com/SogimaYT/launcher-files/blob/main/servers/Naruto-1.7.10/forgemods/required/gkmodlib-of.jar",
            "MD5": "e99ea9363954e53303b6e90b99ab1eee"
          }
        },
        {
          "id": "generated.forgemod:jbra:0.0.0@jar",
          "name": "JBRA",
          "type": "ForgeMod",
          "artifact": {
            "size": 129587,
            "url": "https://github.com/SogimaYT/launcher-files/blob/main/servers/Naruto-1.7.10/forgemods/required/JBRA.jar",
            "MD5": "3e12d9d4d5ee2aba58b0163337fd0a4c"
          }
        },
        {
          "id": "generated.forgemod:journeymap:5.2.7@jar",
          "name": "JourneyMap",
          "type": "ForgeMod",
          "artifact": {
            "size": 8931542,
            "url": "https://github.com/SogimaYT/launcher-files/blob/main/servers/Naruto-1.7.10/forgemods/optionaloff/journeymap-1.7.10-5.2.7-unlimited.jar",
            "MD5": "9cbf4bb1a6eefd2490b81e7693f1bfb0"
          },
          "required": {
            "value": false,
            "def": false
          }
        },
        {
          "id": "generated.forgemod:jrmcore:0.0.0@jar",
          "name": "JRMCore",
          "type": "ForgeMod",
          "artifact": {
            "size": 2535669,
            "url": "https://github.com/SogimaYT/launcher-files/blob/main/servers/Naruto-1.7.10/forgemods/required/JRMCore.jar",
            "MD5": "fb7abf3588833f848f8b2da533f71b7b"
          }
        },
        {
          "id": "generated.forgemod:narutin:1@jar",
          "name": "Naruto Arcane",
          "type": "ForgeMod",
          "artifact": {
            "size": 4803113,
            "url": "https://github.com/SogimaYT/launcher-files/blob/main/servers/Naruto-1.7.10/forgemods/required/NarutoArcane.jar",
            "MD5": "3a3d3b9e7f48a21118b710300694db84"
          }
        },
        {
          "id": "generated.forgemod:menuArcane:NO-GIT-TAG-SET@jar",
          "name": "MenuArcane",
          "type": "ForgeMod",
          "artifact": {
            "size": 668768,
            "url": "https://github.com/SogimaYT/launcher-files/blob/main/servers/Naruto-1.7.10/forgemods/required/NarutoArcane2.jar",
            "MD5": "84f58dce70e7c395b10cbfe1cb24b6ad"
          }
        },
        {
          "id": "generated.forgemod:narutox:0.0.0@jar",
          "name": "NarutoX",
          "type": "ForgeMod",
          "artifact": {
            "size": 1332454,
            "url": "https://github.com/SogimaYT/launcher-files/blob/main/servers/Naruto-1.7.10/forgemods/required/NarutoX.jar",
            "MD5": "fb4a32523560641d4adb585780d386d7"
          }
        },
        {
          "id": "org.spongepowered.asm.launch:npcdbc:1.2.1@jar",
          "name": "CustomNPC+ DBC Addon",
          "type": "ForgeMod",
          "artifact": {
            "size": 5142184,
            "url": "https://github.com/SogimaYT/launcher-files/blob/main/servers/Naruto-1.7.10/forgemods/required/npcdbc-1.2.1.jar",
            "MD5": "0c439bf1f14952c11fb797abbce0c84a"
          }
        },
        {
          "id": "org.spongepowered.asm.launch:npcgecko:1.1@jar",
          "name": "CustomNPC-Plus-Gecko-Addon",
          "type": "ForgeMod",
          "artifact": {
            "size": 40687,
            "url": "https://github.com/SogimaYT/launcher-files/blob/main/servers/Naruto-1.7.10/forgemods/required/npcgecko-1.2.jar",
            "MD5": "49017bffe49d82adac7922bd10c41e59"
          }
        },
        {
          "id": "generated.forgemod:richpresenceMod:1@jar",
          "name": "RichpresenceMod",
          "type": "ForgeMod",
          "artifact": {
            "size": 2074272,
            "url": "https://github.com/SogimaYT/launcher-files/blob/main/servers/Naruto-1.7.10/forgemods/required/rPresence.jar",
            "MD5": "228ceee8cdd9dfbe90ced983517ee825"
          }
        },
        {
          "id": "Arcane.zip",
          "name": "Arcane.zip",
          "type": "File",
          "artifact": {
            "size": 4702711,
            "url": "https://github.com/SogimaYT/launcher-files/blob/main/servers/Naruto-1.7.10/files/resourcepacks/Arcane.zip",
            "MD5": "3753c24212ce6dd7e0921c63eb119ac8",
            "path": "resourcepacks/Arcane.zip"
          }
        },
        {
          "id": "servers.dat",
          "name": "servers.dat",
          "type": "File",
          "artifact": {
            "size": 15155,
            "url": "https://github.com/SogimaYT/launcher-files/blob/main/servers/Naruto-1.7.10/files/servers.dat",
            "MD5": "38c647659fe467b104b52a9753e36913",
            "path": "servers.dat"
          }
        }
      ]
    }
  ]
}
